{
 "id": "B_L6_0039",
 "layer": "L6",
 "arm": "B",
 "exact": true,
 "state_verbatim": true,
 "state_normalized": true,
 "commit_repair": {
  "n_commits": 0,
  "wrong_commits": 0,
  "repaired": 0,
  "unrepaired": 0,
  "wrong_at": []
 },
 "comp_cost": 0.0,
 "done_s": 4.279,
 "U": 0.8029,
 "U_sens": {
  "0.5": 0.8029,
  "1.0": 0.8029,
  "2.0": 0.8029
 },
 "first_response_s": 1.64,
 "n_eou": 3,
 "n_commits": 3,
 "fees": 0,
 "decisions": [
  {
   "i": 0,
   "t_eou": 9.915,
   "ops": [
    {
     "type": "launch",
     "fn": "search_trains",
     "op_id": 2
    },
    {
     "type": "launch",
     "fn": "hold_seat",
     "op_id": 3
    },
    {
     "type": "launch",
     "fn": "purchase_ticket",
     "op_id": 4
    }
   ],
   "say": "好的，马上办。"
  },
  {
   "i": 1,
   "t_eou": 13.355,
   "ops": [
    {
     "type": "patch",
     "op_id": 2,
     "diff": {
      "destination": "Portland"
     }
    }
   ],
   "say": "已更新。"
  },
  {
   "i": 2,
   "t_eou": 18.771,
   "ops": [
    {
     "type": "patch",
     "op_id": 3,
     "diff": {
      "seat_class": "business"
     }
    }
   ],
   "say": "已更新。"
  }
 ],
 "say_events": [
  [
   10.915,
   "好的，马上办。"
  ],
  [
   14.355,
   "已更新。"
  ],
  [
   19.771,
   "已更新。"
  ]
 ],
 "segs": [
  [
   0.5,
   9.275,
   "user"
  ],
  [
   10.915,
   12.715,
   "user"
  ],
  [
   14.981,
   18.131,
   "user"
  ]
 ],
 "armb_timing": {
  "user_overlaps": 0,
  "measured_gaps": [
   1.64,
   2.266
  ]
 }
}