{
 "id": "A_L9_0013",
 "layer": "L9",
 "arm": "A",
 "exact": false,
 "state_verbatim": false,
 "state_normalized": false,
 "commit_repair": {
  "n_commits": 0,
  "wrong_commits": 0,
  "repaired": 0,
  "unrepaired": 0,
  "wrong_at": []
 },
 "comp_cost": 0.0,
 "done_s": 7.917,
 "U": 0.0,
 "U_sens": {
  "0.5": 0.0,
  "1.0": 0.0,
  "2.0": 0.0
 },
 "first_response_s": 1.64,
 "n_eou": 2,
 "n_commits": 1,
 "fees": 0,
 "decisions": [
  {
   "i": 0,
   "t_eou": 5.195,
   "ops": [
    {
     "type": "launch",
     "fn": "schedule_payment",
     "op_id": 2
    }
   ],
   "say": "好的，已为您安排在5月8号支付3000元给房东。"
  },
  {
   "i": 1,
   "t_eou": 18.032,
   "ops": [],
   "say": "已成功在5月8日安排向房东支付3000元。"
  }
 ],
 "say_events": [
  [
   6.195,
   "好的，已为您安排在5月8号支付3000元给房东。"
  ],
  [
   19.032,
   "已成功在5月8日安排向房东支付3000元。"
  ]
 ],
 "segs": [
  [
   0.5,
   4.555,
   "user"
  ],
  [
   16.463,
   17.392,
   "user"
  ]
 ]
}