{
 "id": "A_L9_0004",
 "layer": "L9",
 "arm": "A",
 "exact": true,
 "state_verbatim": true,
 "state_normalized": true,
 "commit_repair": {
  "n_commits": 0,
  "wrong_commits": 0,
  "repaired": 0,
  "unrepaired": 0,
  "wrong_at": []
 },
 "comp_cost": 0.0,
 "done_s": 3.681,
 "U": 0.8279,
 "U_sens": {
  "0.5": 0.8279,
  "1.0": 0.8279,
  "2.0": 0.8279
 },
 "first_response_s": 3.681,
 "n_eou": 2,
 "n_commits": 1,
 "fees": 0,
 "decisions": [
  {
   "i": 0,
   "t_eou": 4.365,
   "ops": [
    {
     "type": "launch",
     "fn": "add_item",
     "op_id": 2
    }
   ],
   "say": "好的，马上办。"
  },
  {
   "i": 1,
   "t_eou": 12.088,
   "ops": [],
   "say": ""
  }
 ],
 "say_events": [
  [
   5.365,
   "好的，马上办。"
  ]
 ],
 "segs": [
  [
   0.5,
   3.725,
   "user"
  ],
  [
   10.323,
   11.448,
   "user"
  ]
 ]
}