{
 "id": "A_L9_0070",
 "layer": "L9",
 "arm": "A",
 "exact": true,
 "state_verbatim": true,
 "state_normalized": true,
 "commit_repair": {
  "n_commits": 0,
  "wrong_commits": 0,
  "repaired": 0,
  "unrepaired": 0,
  "wrong_at": []
 },
 "comp_cost": 0.0,
 "done_s": 42.122,
 "U": 0.1153,
 "U_sens": {
  "0.5": 0.1153,
  "1.0": 0.1153,
  "2.0": 0.1153
 },
 "first_response_s": 1.64,
 "n_eou": 1,
 "n_commits": 1,
 "fees": 0,
 "decisions": [
  {
   "i": 1,
   "t_eou": 33.229,
   "ops": [
    {
     "type": "launch",
     "fn": "save_listing",
     "op_id": 2
    }
   ],
   "say": "正在收藏房源编号 LST47。"
  }
 ],
 "say_events": [
  [
   34.229,
   "正在收藏房源编号 LST47。"
  ]
 ],
 "segs": [
  [
   0.5,
   5.14,
   "user"
  ],
  [
   31.709,
   32.589,
   "user"
  ]
 ]
}