{"e31b67fc7275489bd6c22ea0bb1e09f9a889474897382b3a2b66912dce30603f": {"raw": "{\"dialogue\": \"listen\", \"ops\": [{\"type\":\"launch\",\"fn\":\"track_order\",\"args\":{\"order_id\":\"abc123\"}}], \"say\": \"Sure, let me track your order now.\"}", "infer": 0.748}, "d9d95dd945b328769b4c853179b89ec758416c21d35b045e984e7e2bccb92369": {"raw": "{\"dialogue\": \"listen\", \"ops\": [], \"say\": \"\"}", "infer": 0.284}, "ef5be8397d2dbf4a23be0d9e8881985cc049e3700b9cce8c5e08db07bec3de8c": {"raw": "{\"dialogue\": \"listen\", \"ops\": [], \"say\": \"\"}", "infer": 0.284}, "1aa2480c3d2a9b0d3b490159bd2914ee1ff3539906c04e4d15e280ec6dbf968a": {"raw": "{\"dialogue\": \"listen\", \"ops\": [{\"type\":\"launch\",\"fn\":\"track_order\",\"args\":{\"order_id\":\"DL555\"}}], \"say\": \"Sure, let me track your order now.\"}", "infer": 0.507}, "9fae4ed36e90bb0c0f5ee72c4e2a6c5cd7d8b33157035f542d82792509c7afe2": {"raw": "{\"dialogue\": \"listen\", \"ops\": [{\"type\":\"patch\",\"op_id\":1,\"diff\":{\"order_id\":\"ABC123\"}}], \"say\": \"Updating that to ABC123 and checking the status now.\"}", "infer": 0.55}, "556bd444c8f937594baba99713bf79a2c5dcc3757faf2f312d0c07746fb85af5": {"raw": "{\"dialogue\": \"listen\", \"ops\": [{\"type\":\"launch\",\"fn\":\"search_products\",\"args\":{\"query\":\"wireless headphones\",\"max_price\":100}}], \"say\": \"Searching for wireless headphones under $100 now.\"}", "infer": 0.56}, "d771de68572a2c91bb472e1636e50e23a05a0d850223d29397b8a566377b8cfd": {"raw": "{\"dialogue\": \"listen\", \"ops\": [{\"type\":\"launch\",\"fn\":\"track_order\",\"args\":{\"order_id\":\"XYZ88\"}}], \"say\": \"Sure, let me check the status of your order now.\"}", "infer": 0.524}, "1959c9ccc84fa61908d56e2a7f88cd83ea4540feb832abfd59c4c2b75bf3fe1e": {"raw": "{\"dialogue\": \"listen\", \"ops\": [], \"say\": \"\"}", "infer": 0.286}, "8f570eaef9ee1f79796bf72ab624a5defb55741b78a8631a6cd701a38c7189e3": {"raw": "{\"dialogue\": \"listen\", \"ops\": [], \"say\": \"\"}", "infer": 0.283}, "c3cdb50da549a8281f28a19f3a1286fc1e9c635eb04eb6fe1b37f166c7991310": {"raw": "{\"dialogue\": \"listen\", \"ops\": [], \"say\": \"\"}", "infer": 0.274}, "fe4e7ac3262b40a83ffab0708b74b85a1a56da77b49772e7b778434f08c37f65": {"raw": "{\"dialogue\": \"listen\", \"ops\": [], \"say\": \"\"}", "infer": 0.274}, "0da2c8e6b1d51fd3f7a650e573e1fecbeeb2781ee53d5cb4b2e8393c8db4c8c5": {"raw": "{\"dialogue\": \"listen\", \"ops\": [{\"type\":\"launch\",\"fn\":\"search_products\",\"args\":{\"query\":\"desk\"}}], \"say\": \"Searching for desks now.\"}", "infer": 0.449}, "8df8ed5b90d13452c2d62a10e6458d3f0dc744731e53689401db353b2f7a07cf": {"raw": "{\"dialogue\": \"listen\", \"ops\": [{\"type\":\"patch\",\"op_id\":1,\"diff\":{\"args\":{\"max_price\":300}}}, {\"type\":\"commit\",\"op_id\":1}], \"say\": \"Updating that to under $300 and checking now.\"}", "infer": 0.611}, "ddc4083734a61ce44033732a22dc4d27cbab1b30195eebc9edcb8e51efd56337": {"raw": "{\"dialogue\": \"listen\", \"ops\": [], \"say\": \"\"}", "infer": 0.311}, "151297d35a66e9597038f470427c938f3b32678d490792482973673281049fa6": {"raw": "{\"dialogue\": \"listen\", \"ops\": [{\"type\":\"launch\",\"fn\":\"add_to_cart\",\"args\":{\"product_id\":\"K2\",\"quantity\":2}}], \"say\": \"Adding two K2 items to your cart now.\"}", "infer": 0.548}, "2bebe8e7aee88b0de093ccf4efcf29e3a9bca25aef9e54f24dd02044b86802fa": {"raw": "{\"dialogue\": \"listen\", \"ops\": [{\"type\":\"launch\",\"fn\":\"track_order\",\"args\":{\"order_id\":\"FAST99\"}}], \"say\": \"Tracking your order now.\"}", "infer": 0.482}, "44d057c770187cf58145f0a64e7df746537da7ab5428675c04353faed28e657a": {"raw": "{\"dialogue\": \"listen\", \"ops\": [], \"say\": \"\"}", "infer": 0.274}, "4461eba0031343b03b89605c30561f1de0f590f151cdf518e7eebb7c1297d691": {"raw": "{\"dialogue\": \"listen\", \"ops\": [{\"type\":\"launch\",\"fn\":\"search_products\",\"args\":{\"query\":\"mechanical keyboard\",\"max_price\":null}}], \"say\": \"Searching for mechanical keyboards now.\"}", "infer": 0.502}, "2b800ffba2c4250e74f3c2f56624df45e97c2143f213707ba5f4dea7265da5ba": {"raw": "{\"dialogue\": \"listen\", \"ops\": [{\"type\":\"patch\",\"op_id\":1,\"diff\":{\"args\":{\"max_price\":200}}}, {\"type\":\"commit\",\"op_id\":1}], \"say\": \"Updating that to under $200 and checking now.\"}", "infer": 0.608}, "2bad4f2fa83522767105a3eea56e616f4248cb3c432280f8a0e301e6f2aab000": {"raw": "{\"dialogue\": \"listen\", \"ops\": [], \"say\": \"\"}", "infer": 0.275}, "54c04f3670ab1c6e5ae95130dd108f6a09f9f1d9cc5051ff29b54fef5a64b560": {"raw": "{\"dialogue\": \"listen\", \"ops\": [{\"type\":\"launch\",\"fn\":\"search_products\",\"args\":{\"query\":\"mechanical keyboard\",\"max_price\":200}}], \"say\": \"Searching for mechanical keyboards under $200 now.\"}", "infer": 0.557}, "e1f3057b0bc5b4bac902e9638a85ed1c6b13e818275c02484b108ffb16e83bdd": {"raw": "{\"dialogue\": \"listen\", \"ops\": [], \"say\": \"\"}", "infer": 0.27}, "92e61076d9413984e33335e9fef1489ca6a43f0e73e9849bc3a72d60fb56bc25": {"raw": "{\"dialogue\": \"listen\", \"ops\": [{\"type\":\"launch\",\"fn\":\"search_products\",\"args\":{\"query\":\"hiking boots\"}}], \"say\": \"Sure, searching for hiking boots now.\"}", "infer": 0.476}, "91ca64f18e5e6447e4b466ce45b5a0087a82f92013849ba5c8706125e84580c0": {"raw": "{\"dialogue\": \"listen\", \"ops\": [{\"type\":\"launch\",\"fn\":\"track_order\",\"args\":{\"order_id\":\"123abc\"}}], \"say\": \"Tracking your order now.\"}", "infer": 0.463}, "fb5e2d30e381294b8b9c79a4284bfa2ba7e6e172af834fb20edcf409cfd1bfad": {"raw": "{\"dialogue\": \"listen\", \"ops\": [{\"type\":\"launch\",\"fn\":\"search_products\",\"args\":{\"query\":\"winter jackets\",\"max_price\":150}}, {\"type\":\"commit\",\"op_id\":1}], \"say\": \"Tracking your order and searching for winter jackets now.\"}", "infer": 0.615}, "019067188805544469a04c86b306cf341a07dde81a1d480af169b5018b3e9fed": {"raw": "{\"dialogue\": \"listen\", \"ops\": [{\"type\":\"launch\",\"fn\":\"add_to_cart\",\"args\":{\"product_id\":\"B7\",\"quantity\":1}}], \"say\": \"Adding one B7 to your cart now.\"}", "infer": 0.513}, "36fe0bb450fbab55aaa4098bdc0fc6f11c77e569687f8066df477bbe725612ac": {"raw": "{\"dialogue\": \"listen\", \"ops\": [], \"say\": \"\"}", "infer": 0.278}, "303087a6d79f8b470f618ba2512701a6da4dcd1385a25e3e8a7d4c8ad7d4f8af": {"raw": "{\"dialogue\": \"listen\", \"ops\": [{\"type\":\"launch\",\"fn\":\"search_products\",\"args\":{\"query\":\"gadgets and tech stuff\"}}], \"say\": \"Looking for gadgets and tech stuff for you.\"}", "infer": 0.497}, "ca5aee78ad80303cb5ff4300bd96176c4b2c00b2daf5f67006216c81d5f00268": {"raw": "{\"dialogue\": \"listen\", \"ops\": [{\"type\":\"launch\",\"fn\":\"add_to_cart\",\"args\":{\"product_id\":\"K-2\",\"quantity\":1}},{\"type\":\"launch\",\"fn\":\"track_order\",\"args\":{\"order_id\":\"D-E-L-I-V\"}}], \"say\": \"Adding K-2 to your cart and tracking order D-E-L-I-V now.\"}", "infer": 0.756}, "b16e2043c6139bb6cdb4a59fbc7cac2cfdcb7d2b2796a9fef0ab979cd67a0f33": {"raw": "{\"dialogue\": \"listen\", \"ops\": [], \"say\": \"\"}", "infer": 0.263}, "98ac62bf2cad63dd79f2d494138d56773978f22798ab1ee09beac3d2796df812": {"raw": "{\"dialogue\": \"listen\", \"ops\": [], \"say\": \"\"}", "infer": 0.261}, "68aead59780b14450f96283d860d96fb113a4e3a3debb325ad5e3ad5a92e9a1a": {"raw": "{\"dialogue\": \"listen\", \"ops\": [{\"type\":\"launch\",\"fn\":\"add_to_cart\",\"args\":{\"product_id\":\"K2\",\"quantity\":1}},{\"type\":\"launch\",\"fn\":\"track_order\",\"args\":{\"order_id\":\"DE\"}}], \"say\": \"Adding item K2 to your cart now and checking on order DE.\"}", "infer": 0.699}, "53918022a9254f7f2e46f0d5e4b1b7e2e02020f372bb37945b9d55e3225554ac": {"raw": "{\"dialogue\": \"listen\", \"ops\": [], \"say\": \"\"}", "infer": 0.301}, "43f8fc4c386352c587de810da2f90bce30f478c834f1942938bd8d189125767f": {"raw": "{\"dialogue\": \"listen\", \"ops\": [], \"say\": \"\"}", "infer": 0.271}, "839a0c1d749c0e36ad175d4cb2e608e5063e7f02fdec0c5a3bc368f0b851013a": {"raw": "{\"dialogue\": \"listen\", \"ops\": [{\"type\":\"launch\",\"fn\":\"add_to_cart\",\"args\":{\"product_id\":\"P-5-2\",\"quantity\":2}}], \"say\": \"Adding two P-5-2 items to your cart now.\"}", "infer": 0.58}, "95348384ce8b263ef4df09b5f7768276bf66480dabeba6a7793dfa7452acbbba": {"raw": "{\"dialogue\": \"listen\", \"ops\": [], \"say\": \"\"}", "infer": 0.264}, "3ad02c18c59a7e233b70de82d6f1d2395f54b885c9fe2dabd7cd5f091f86c4f0": {"raw": "{\"dialogue\": \"listen\", \"ops\": [], \"say\": \"\"}", "infer": 0.266}, "9f832dd709ae7958fd4677654cf1d64022667a09457eb5413c3e19668f0419af": {"raw": "{\"dialogue\": \"listen\", \"ops\": [], \"say\": \"\"}", "infer": 0.272}, "434847e96c637cd7bfc7cdde36ff542f995d89fda66a3d5c0b5a97c5f9d397db": {"raw": "{\"dialogue\": \"listen\", \"ops\": [], \"say\": \"\"}", "infer": 0.278}, "b6dbc88cec469a487573a81df775a20491531446eee1634e596abb30a7770977": {"raw": "{\"dialogue\": \"listen\", \"ops\": [{\"type\":\"launch\",\"fn\":\"add_to_cart\",\"args\":{\"product_id\":\"P52\",\"quantity\":2}}], \"say\": \"Adding two P52 items to your cart now.\"}", "infer": 0.555}, "fccf6da35d69a7f84401540099beff521ff8093cd963c1252737d25881931577": {"raw": "{\"dialogue\": \"listen\", \"ops\": [], \"say\": \"\"}", "infer": 0.332}, "1eb1c1e766a78d5eaf99c5ba301a3f174b6d265397c9c390d2765e283e70e476": {"raw": "{\"dialogue\": \"listen\", \"ops\": [{\"type\":\"launch\",\"fn\":\"track_order\",\"args\":{\"order_id\":\"DL555\"}}], \"say\": \"Tracking your order now.\"}", "infer": 0.46}, "f34bd74fb721c7a10452207f3a855baa797e0fcedb2a194716a4419c752be57b": {"raw": "{\"dialogue\": \"listen\", \"ops\": [{\"type\":\"launch\",\"fn\":\"track_order\",\"args\":{\"order_id\": \"BOB12\"}}], \"say\": \"Tracking order BOB12 for you now.\"}", "infer": 0.53}, "505714b699338206903abd1d1eeb2c2de8faf4793bfd6b29f5c4808faebe87ea": {"raw": "{\"dialogue\": \"listen\", \"ops\": [{\"type\": \"launch\", \"fn\": \"track_order\", \"args\": {\"order_id\": \"BOB12\"}}], \"say\": \"\"}", "infer": 0.468}, "b91f44ab117452bb92117bd5d1afdb71de15cca2844dbcf3e76e84c16333ba11": {"raw": "{\"dialogue\": \"listen\", \"ops\": [{\"type\":\"launch\",\"fn\":\"track_order\",\"args\":{\"order_id\":\"BOB12\"}}], \"say\": \"Tracking your order BOB12 now.\"}", "infer": 0.502}, "6b603a763bf7076a23313acf342c0d502c7ceb5172513c6b85295cd081e284ee": {"raw": "{\"dialogue\": \"listen\", \"ops\": [], \"say\": \"\"}", "infer": 0.267}, "d80e93f77ddcc215a152df75ee4f482994cb418d1f2aaca1c85b83c3b6a77456": {"raw": "{\"dialogue\": \"listen\", \"ops\": [{\"type\":\"launch\",\"fn\":\"search_products\",\"args\":{\"query\":\"coffee maker\",\"max_price\":50}}], \"say\": \"Searching for coffee makers under $50 now.\"}", "infer": 0.527}, "25ff8d38f930cfe7106540301a09967ede9a9608985b60bf0169e466f5ef29d0": {"raw": "{\"dialogue\": \"listen\", \"ops\": [{\"type\":\"launch\",\"fn\":\"track_order\",\"args\":{\"order_id\":\"GG5\"}}]}", "infer": 0.377}, "4bdf3e98165a38276a869d2bef6a4ea548767fbf6c8b82395ddcaac3bc227fe1": {"raw": "{\"dialogue\": \"listen\", \"ops\": [{\"type\":\"launch\",\"fn\":\"search_products\",\"args\":{\"query\":\"gaming mouse\"}},{\"type\":\"launch\",\"fn\":\"track_order\",\"args\":{\"order_id\":\"PO999\"}}], \"say\": \"\"}", "infer": 0.569}, "0721dd2085bfa8c5a03793e37820b59842820de6fff1e08784a1c9fda4c03812": {"raw": "{\"dialogue\": \"listen\", \"ops\": [{\"type\":\"launch\",\"fn\":\"search_products\",\"args\":{\"query\":\"tablet\"}}], \"say\": \"Searching for tablets now.\"}", "infer": 0.44}, "c4f2d203aef5631c1a6ede05899f55c7922c71e9445973c017dc10a5f6529909": {"raw": "{\"dialogue\": \"stay\", \"ops\": [{\"type\":\"patch\",\"op_id\":1,\"diff\":{\"args\":{\"query\":\"tablet\"}}},{\"type\":\"launch\",\"fn\":\"add_to_cart\",\"args\":{\"product_id\":\"$RESULT_1.products[0].product_id\",\"quantity\":1}}],\"say\": \"Updating to search for a tablet and adding one to the cart.\"}", "infer": 0.747}, "72a1a5d4f4f195440c4865fbd0cc24a868b597c0581c8ec0e1cdd7711bf5fcaf": {"raw": "{\"dialogue\": \"listen\", \"ops\": [], \"say\": \"\"}", "infer": 0.282}, "1b044eb08e3a559208d8c57d67fca1136d6d8158ab093ec133d8dfae2592244a": {"raw": "{\"dialogue\": \"listen\", \"ops\": [{\"type\":\"launch\",\"fn\":\"search_products\",\"args\":{\"query\":\"coffee maker\",\"max_price\":50}},{\"type\":\"launch\",\"fn\":\"track_order\",\"args\":{\"order_id\":\"WWW\"}}], \"say\": \"Searching for coffee makers under $50 and tracking your order.\"}", "infer": 0.707}, "2207bda92c3a6baf6c4e951a45c8c185fcbc152e768dbf2cafce157e33657758": {"raw": "{\"dialogue\": \"listen\", \"ops\": [], \"say\": \"\"}", "infer": 0.273}, "d220645b71d46f053a3fefdbd33cc340d3ceb1e28bc784065998afb732f95210": {"raw": "{\"dialogue\": \"listen\", \"ops\": [], \"say\": \"\"}", "infer": 0.263}, "15967c5fd6f4046a94d65b663611d568fc0729cb642310beb933488ff787d0a2": {"raw": "{\"dialogue\": \"listen\", \"ops\": [{\"type\":\"launch\",\"fn\":\"track_order\",\"args\":{\"order_id\":\"BOB\"}}], \"say\": \"Tracking order BOB for you now.\"}", "infer": 0.475}, "a12970375fe4a1531eaef8d974ace12f18e061ca6f719660e201c3e928340ead": {"raw": "{\"dialogue\": \"listen\", \"ops\": [{\"type\":\"commit\",\"op_id\":1},{\"type\":\"launch\",\"fn\":\"search_products\",\"args\":{\"query\":\"nice watch\",\"max_price\":200}},{\"type\":\"noop\"}], \"say\": \"Tracking your order now. Searching for watches under $200.\"}", "infer": 0.688}, "881aad7ae2983cf30c2e182f183a45b1d2df1f9bc085bf984bc6dc140f9cac58": {"raw": "{\"dialogue\": \"listen\", \"ops\": [], \"say\": \"\"}", "infer": 0.272}, "918282dff01d61a6f22395968706c61c945e668ed32e490042ec226c3595b8e2": {"raw": "{\"dialogue\": \"listen\", \"ops\": [], \"say\": \"\"}", "infer": 0.265}, "70e28f20df17e7e58b3b5c69f063289858f0da9b75f319495683881a52d06768": {"raw": "{\"dialogue\": \"listen\", \"ops\": [{\"type\": \"launch\", \"fn\": \"track_order\", \"args\": {\"order_id\": \"POP\"}}], \"say\": \"\"}", "infer": 0.453}, "1167c61ea9b024ac8748b119806806bfec85bc6a58015a9a39022aa6324c3aaa": {"raw": "{\"dialogue\": \"listen\", \"ops\": [{\"type\":\"launch\",\"fn\":\"track_order\",\"args\":{\"order_id\": \"POP\"}}], \"say\": \"\"}", "infer": 0.415}, "37ea0daab5ab32d215592b4b0d6d2371d041d694754efcbde82d118c64cc9feb": {"raw": "{\"dialogue\": \"listen\", \"ops\": [{\"type\":\"launch\",\"fn\":\"track_order\",\"args\":{\"order_id\": \"POP\"}}, {\"type\":\"launch\",\"fn\":\"search_products\",\"args\":{\"query\": \"nice watch\", \"max_price\": 200}}], \"say\": \"\"}", "infer": 0.639}, "0f6b2029e219de2fb656230d2b71dadfe8ff2967471c58cb3c33e1a69947c484": {"raw": "{\"dialogue\": \"listen\", \"ops\": [{\"type\":\"launch\",\"fn\":\"track_order\",\"args\":{\"order_id\":\"POP\"}},{\"type\":\"patch\",\"op_id\":1,\"diff\":{\"query\":\"nice watch\",\"max_price\":200}}],\"say\": \"Tracking your order POP now and searching for a nice watch under $200.\"}", "infer": 0.727}, "3fdfd4535ee595a98ed75eace3149e835f785773bfc81f36d08c1960e4204bc0": {"raw": "{\"dialogue\": \"listen\", \"ops\": [{\"type\":\"launch\",\"fn\":\"track_order\",\"args\":{\"order_id\":\"GG5\"}}]}", "infer": 0.379}, "c9170c48f1fc7e587934b48c7f7c0d638e3913e30945f7856c7ed2668ec45058": {"raw": "{\"dialogue\": \"listen\", \"ops\": [{\"type\":\"launch\",\"fn\":\"track_order\",\"args\":{\"order_id\": \"GG5\"}}], \"say\": \"Tracking order GG5 now.\"}", "infer": 0.463}, "4c7906fd0e2d34e52907c3a6827b1807312a664024944a652dcb43b962beb50f": {"raw": "{\"dialogue\": \"listen\", \"ops\": [{\"type\":\"launch\",\"fn\":\"track_order\",\"args\":{\"order_id\": \"GG5\"}}, {\"type\":\"launch\",\"fn\":\"add_to_cart\",\"args\":{\"product_id\": \"X1\", \"quantity\": 1}}], \"say\": \"\"}", "infer": 0.647}, "031911b3be9fd73e4d9446ddac30234839b3e7620200ced210f0ef14b98894b0": {"raw": "{\"dialogue\": \"listen\", \"ops\": [], \"say\": \"\"}", "infer": 0.275}, "e83a9d8d854d89788aaba4ed7a99da48c4214216a98ecb4f943f15145c08f2e5": {"raw": "{\"dialogue\": \"listen\", \"ops\": [], \"say\": \"\"}", "infer": 0.265}, "fe56f3f1e983ebf71190105fbc0ac3b16b57fbdf410ca222bfb5c2ddebe0590c": {"raw": "{\"dialogue\": \"listen\", \"ops\": [{\"type\":\"launch\",\"fn\":\"track_order\",\"args\":{\"order_id\":\"CAT\"}},{\"type\":\"launch\",\"fn\":\"search_products\",\"args\":{\"query\":\"cat food\"}},{\"type\":\"launch\",\"fn\":\"add_to_cart\",\"args\":{\"product_id\":\"\",\"quantity\":3}}], \"say\": \"\"}", "infer": 0.694}, "f475fc96fbe160ea9396d589bd91499236cfda62e7fba37c9d0c797ce25f4988": {"raw": "{\"dialogue\": \"listen\", \"ops\": [], \"say\": \"\"}", "infer": 0.272}, "f7de61a40c5c1874192bcad39efc90a8250e344070f0682f0bf02221953668c5": {"raw": "{\"dialogue\": \"listen\", \"ops\": [], \"say\": \"\"}", "infer": 0.275}, "c192127c799b306afec62f42f22c296b7104c04c3752920162be805cfb0119e5": {"raw": "{\"dialogue\": \"listen\", \"ops\": [], \"say\": \"\"}", "infer": 0.279}, "3d21ce29f18c1df31b356a8ed05eedf523da593211d302beab9a089bdda95dfa": {"raw": "{\"dialogue\": \"listen\", \"ops\": [{\"type\":\"launch\",\"fn\":\"track_order\",\"args\":{\"order_id\":\"CAT\"}}], \"say\": \"Tracking your order CAT now.\"}", "infer": 0.448}, "f872d05961e7ffece77d87037a4df3f9064ad08701725b7718cfb1c72cb31c96": {"raw": "{\"dialogue\": \"listen\", \"ops\": [{\"type\":\"cancel\",\"op_id\":1},{\"type\":\"launch\",\"fn\":\"search_products\",\"args\":{\"query\":\"cat food\"}}, {\"type\":\"launch\",\"fn\":\"track_order\",\"args\":{\"order_id\": \"CAT\"}}], \"say\": \"\"}", "infer": 0.619}, "8c95b362f7ab2868b7bbcc315dd869491b0286e28a8b739af13b817889fb2349": {"raw": "{\"dialogue\": \"listen\", \"ops\": [], \"say\": \"\"}", "infer": 0.297}, "5985daebf02c145ab6b9696dabdc7d01ac3f374017698a131dff04902c00ebc4": {"raw": "{\"dialogue\": \"listen\", \"ops\": [], \"say\": \"\"}", "infer": 0.272}, "63f2cf377baa15d4441b7a2ba2951fe8081a5d18b3ab3c8a240198e9fff9e834": {"raw": "{\"dialogue\": \"listen\", \"ops\": [{\"type\": \"launch\", \"fn\": \"get_exchange_rate\", \"args\": {\"amount\": 500, \"from_currency\": \"USD\", \"to_currency\": \"EUR\"}}], \"say\": \"\"}", "infer": 0.572}, "1d4a4203cdc45c5edc1f7410181e2084328c5714e2d48f697f5a7fc00d14327e": {"raw": "{\"dialogue\": \"listen\", \"ops\": [{\"type\":\"launch\",\"fn\":\"get_exchange_rate\",\"args\":{\"amount\":500,\"from_currency\":\"USD\",\"to_currency\":\"EUR\"}}], \"say\": \"Sure, let me check the current exchange rate for you.\"}", "infer": 0.578}, "eeeab2f172b0ae85e0c3c60a8bb3dfbacba69bfedf3f16087b3c39195792b2f6": {"raw": "{\"dialogue\": \"listen\", \"ops\": [{\"type\":\"launch\",\"fn\":\"get_card_benefits\",\"args\":{\"card_type\":\"premium\"}}], \"say\": \"Sure, let me check your premium card benefits now.\"}", "infer": 0.502}, "08a71223290f2f002eb2cbe0eea87d2f7d19fccaaed9cbf87e9a8b5719a8bd2f": {"raw": "{\"dialogue\": \"listen\", \"ops\": [{\"type\":\"patch\",\"op_id\":1,\"diff\":{\"card_type\":\"platinum\"}}], \"say\": \"Updating that to platinum and checking the benefits now.\"}", "infer": 0.48}, "a436052191936645467b3416b28f81d44b0e26b337db1bfbd45264bdd26986e6": {"raw": "{\"dialogue\": \"listen\", \"ops\": [{\"type\":\"launch\",\"fn\":\"modify_autopay\",\"args\":{\"bill_type\":\"mortgage\",\"source_account\":\"savings\"}}], \"say\": \"Updating your mortgage autopay to pull from savings now.\"}", "infer": 0.559}, "b6e60cb00254e12559da725cdc12e520d881c354c8c1c53a30b222acfcb018ab": {"raw": "{\"dialogue\": \"listen\", \"ops\": [], \"say\": \"\"}", "infer": 0.27}, "1a1e05b1405caa77e6c4469215b39d0a5ca5d577410a0c10a9437b18ef17a9a3": {"raw": "{\"dialogue\": \"listen\", \"ops\": [], \"say\": \"\"}", "infer": 0.269}, "a8f591fe181975bbf08e7b32dd250cfeb2ffa20f8c72d737eb90bfa3c7181f8e": {"raw": "{\"dialogue\": \"listen\", \"ops\": [{\"type\":\"launch\",\"fn\":\"modify_autopay\",\"args\":{\"bill_type\":\"mortgage\",\"source_account\":\"savings\"}}], \"say\": \"Updating your mortgage autopay to pull from savings now.\"}", "infer": 0.56}, "12d672d0000e7196fb041260394028efc8b3b1f8d412ff51c1e8537ccd9d1154": {"raw": "{\"dialogue\": \"listen\", \"ops\": [{\"type\":\"launch\",\"fn\":\"get_exchange_rate\",\"args\":{\"amount\":1000,\"from_currency\":\"USD\"}}], \"say\": \"Calculating the exchange rate for 1,000 USD now.\"}", "infer": 0.57}, "00bd8f756a062d3171eccacb41bd11fe7d9ba9b5ef3bd96f6b78b42fa515fe8b": {"raw": "{\"dialogue\": \"listen\", \"ops\": [], \"say\": \"\"}", "infer": 0.277}, "d1431427a4d4e82059974dee517edcde80d91ea40fe0672f492ee5f9479c3141": {"raw": "{\"dialogue\": \"listen\", \"ops\": [{\"type\":\"launch\",\"fn\":\"get_card_benefits\",\"args\":{\"card_type\":\"travel\"}}], \"say\": \"Let me check the benefits for your travel card.\"}", "infer": 0.502}, "6ef543701453fe62cfc5876970b69f53139312cee84b849e5afefc04ead6cc00": {"raw": "{\"dialogue\": \"listen\", \"ops\": [{\"type\":\"commit\",\"op_id\":1}], \"say\": \"I'm retrieving the benefits for your travel card now.\"}", "infer": 0.426}, "1ab1d3ea2d4c547d34105ef5b6f053ec4c1d0e1c19b458d963367116a5fe299f": {"raw": "{\"dialogue\": \"listen\", \"ops\": [{\"type\":\"launch\",\"fn\":\"modify_autopay\",\"args\":{\"bill_type\":\"mortgage\",\"source_account\":\"savings\"}}], \"say\": \"Setting up your mortgage autopay from savings now.\"}", "infer": 0.566}, "ccdb1dc5f8795092cce45655a239ccd56269206140dc0ac00d6492d1d70991bd": {"raw": "{\"dialogue\": \"listen\", \"ops\": [], \"say\": \"\"}", "infer": 0.277}, "2ba2e2c79f2a0a90129072f705cb2aa37bfbd34a1a8c0a921640bc0c0dd4d632": {"raw": "{\"dialogue\": \"listen\", \"ops\": [{\"type\":\"launch\",\"fn\":\"modify_autopay\",\"args\":{\"bill_type\":\"mortgage\",\"source_account\":\"savings\"}}], \"say\": \"Setting up your mortgage autopay from savings now.\"}", "infer": 0.551}, "572715f2512d9bbe2c4736649ca30101de51bcf5d5eaccb481b3e4701b43c650": {"raw": "{\"dialogue\": \"listen\", \"ops\": [{\"type\": \"launch\", \"fn\": \"get_exchange_rate\", \"args\": {\"amount\": 200, \"from_currency\": \"EUR\", \"to_currency\": \"USD\"}}], \"say\": \"\"}", "infer": 0.576}, "d9e288d4fbd6d7e8d35575529af33cfc7f7ea1e907476593b21f7c2199f0be7b": {"raw": "{\"dialogue\": \"listen\", \"ops\": [], \"say\": \"\"}", "infer": 0.278}, "4352d2c1f4db74700e8833264386198fb52b2e61f8a6e5de4e68a18a9676f8ed": {"raw": "{\"dialogue\": \"listen\", \"ops\": [{\"type\": \"launch\", \"fn\": \"get_exchange_rate\", \"args\": {\"amount\": 200, \"from_currency\": \"EUR\", \"to_currency\": \"USD\"}}], \"say\": \"\"}", "infer": 0.563}, "17b8f0fe3562948fdf99bbb5a388c9054c4f7ad7c3205b4ca17f34feba957bda": {"raw": "{\"dialogue\": \"listen\", \"ops\": [], \"say\": \"\"}", "infer": 0.285}, "9c80e7d9b4a8496f31ff18e4974d2ceb63bab65773d9510db29f38513c1eca20": {"raw": "{\"dialogue\": \"listen\", \"ops\": [{\"type\":\"launch\",\"fn\":\"get_card_benefits\",\"args\":{\"card_type\":\"travel\"}}, {\"type\":\"launch\",\"fn\":\"get_exchange_rate\",\"args\":{\"amount\":200,\"from_currency\":\"GBP\",\"to_currency\":\"JPY\"}}], \"say\": \"Sure, I'll check both for you now.\"}", "infer": 0.745}, "10cc4ba31290e6c8b100c9fededed43626560952af67723b68cb3483125bf7d5": {"raw": "{\"dialogue\": \"listen\", \"ops\": [{\"type\":\"launch\",\"fn\":\"modify_autopay\",\"args\":{\"bill_type\":\"credit card\",\"source_account\":\"savings\"}}], \"say\": \"Switching your credit card autopay to savings now.\"}", "infer": 0.554}, "a0d2dfd44d981baabb3ed79ad6d0dd19bb8f4954918ad68b1aca7aaa84ac0f8c": {"raw": "{\"dialogue\": \"listen\", \"ops\": [{\"type\":\"launch\",\"fn\":\"get_exchange_rate\",\"args\":{\"amount\":150,\"from_currency\":\"EUR\",\"to_currency\":\"USD\"}}], \"say\": \"Calculating 150 euros to US dollars now.\"}", "infer": 0.583}, "d2a51456ce32bc719251355efe3c75bb10c5c9384690caa08280305062ddc0e3": {"raw": "{\"dialogue\": \"listen\", \"ops\": [{\"type\":\"launch\",\"fn\":\"get_exchange_rate\",\"args\":{\"amount\":100,\"from_currency\":\"EUR\",\"to_currency\":\"USD\"}}], \"say\": \"Calculating the exchange rate now.\"}", "infer": 0.544}, "8f0f2c0473b952a96d4755b1a138c64d967db64721689a5de5b3ea28e22d6ad5": {"raw": "{\"dialogue\": \"listen\", \"ops\": [{\"type\":\"patch\",\"op_id\":1,\"diff\":{\"amount\":150}}], \"say\": \"Updating that to 150 euros and recalculating now.\"}", "infer": 0.522}, "d434bd48956257e5fac51acdccc24f915f31b0af1e04ba3778ac0ecd87e57291": {"raw": "{\"dialogue\": \"listen\", \"ops\": [{\"type\":\"launch\",\"fn\":\"get_exchange_rate\",\"args\":{\"amount\":50,\"from_currency\":\"USD\",\"to_currency\":\"EUR\"}},{\"type\":\"launch\",\"fn\":\"get_exchange_rate\",\"args\":{\"amount\":100,\"from_currency\":\"CAD\",\"to_currency\":\"USD\"}}],\"say\": \"\"}", "infer": 0.691}, "07951f5dcba5cf450ddd79ffdeeb3945408bb8f8c9328eb58aa89f4a459c705d": {"raw": "{\"dialogue\": \"stay\", \"ops\": [], \"say\": \"\"}", "infer": 0.282}, "118a2855bfd2ea9cb465bf1cbe9e0c7947b2d90f06185e2f14af6d0c3b02a18a": {"raw": "{\"dialogue\": \"listen\", \"ops\": [{\"type\":\"launch\",\"fn\":\"modify_autopay\",\"args\":{\"bill_type\":\"mortgage\",\"source_account\":\"savings\"}}], \"say\": \"Switching your mortgage autopay to pull from savings now.\"}", "infer": 0.564}, "b6c831d31ccf97415d0ff4972cd443617e61b5e40bca4b4a4126ea0f28e92ef2": {"raw": "{\"dialogue\": \"listen\", \"ops\": [], \"say\": \"\"}", "infer": 0.269}, "3b9da6344e7aa37c6ddc46a39afbf7159119876cf148a95305185d939850762f": {"raw": "{\"dialogue\": \"listen\", \"ops\": [{\"type\": \"launch\", \"fn\": \"get_exchange_rate\", \"args\": {\"amount\": 500, \"from_currency\": \"JPY\", \"to_currency\": \"USD\"}}], \"say\": \"\"}", "infer": 0.571}, "7a369d338a87bfb69d930a809695705b0cf0cb3fb408664e9df3ca513b678049": {"raw": "{\"dialogue\": \"listen\", \"ops\": [{\"type\":\"launch\",\"fn\":\"get_card_benefits\",\"args\":{\"card_type\":\"gold\"}}], \"say\": \"Sure, let me check the benefits for your gold card now.\"}", "infer": 0.523}, "2ef691c75edccc5fcf67619e95f5a0807b76d6b0732025826017c477e813c8aa": {"raw": "{\"dialogue\": \"listen\", \"ops\": [{\"type\":\"launch\",\"fn\":\"get_exchange_rate\",\"args\":{\"amount\":1000,\"from_currency\":\"USD\",\"to_currency\":\"EUR\"}},{\"type\":\"launch\",\"fn\":\"modify_autopay\",\"args\":{\"bill_type\":\"credit_card\",\"source_account\":\"savings\"}},{\"type\":\"launch\",\"fn\":\"get_card_benefits\",\"args\":{\"card_type\":\"premium\"}}], \"say\": \"\"}", "infer": 0.855}, "f9af0037d44243441f48c25a2924dfbadde98c93e06fcdd64ebff961ae63bd52": {"raw": "{\"dialogue\": \"listen\", \"ops\": [{\"type\":\"launch\",\"fn\":\"get_exchange_rate\",\"args\":{\"amount\":300,\"from_currency\":\"EUR\",\"to_currency\":\"GBP\"}}]}", "infer": 0.46}, "c34f6be23aa9f119fc9c7d5c0f2546295cfddcad288654fad4f81f8c93f00309": {"raw": "{\"dialogue\": \"listen\", \"ops\": [{\"type\":\"launch\",\"fn\":\"get_exchange_rate\",\"args\":{\"amount\":1000,\"from_currency\":\"USD\",\"to_currency\":\"EUR\"}}], \"say\": \"Checking the current USD to EUR exchange rate now.\"}", "infer": 0.596}, "0df820378d70c4843fb05c47763c82a4df14a9862d9486ad04b531177d3f6eb4": {"raw": "{\"dialogue\": \"listen\", \"ops\": [{\"type\":\"launch\",\"fn\":\"get_card_benefits\",\"args\":{\"card_type\":\"gold\"}}], \"say\": \"Checking the benefits for your gold card now.\"}", "infer": 0.497}, "2b9b141903993918f8a894e4183832d8f4f30efb0dc42cfcc4bb7275827bddf0": {"raw": "{\"dialogue\": \"listen\", \"ops\": [{\"type\":\"launch\",\"fn\":\"get_card_benefits\",\"args\":{\"card_type\": \"gold\"}}, {\"type\":\"launch\",\"fn\":\"get_exchange_rate\",\"args\":{\"amount\": 500, \"from_currency\": \"USD\", \"to_currency\": \"JPY\"}}], \"say\": \"\"}", "infer": 0.707}, "aa2e629316f2a48ee07374b148280abfe7fa3124a4f5939afaa26ba0577d2023": {"raw": "{\"dialogue\": \"listen\", \"ops\": [{\"type\":\"launch\",\"fn\":\"modify_autopay\",\"args\":{\"bill_type\":\"mortgage\",\"source_account\":\"savings\"}}], \"say\": \"Updating your mortgage autopay to pull from savings now.\"}", "infer": 0.556}, "d8d7d8640119aa7cdb13fcf0ae2cdb00871c3021230eb57ff4c44874f948724b": {"raw": "{\"dialogue\": \"listen\", \"ops\": [{\"type\":\"launch\",\"fn\":\"modify_autopay\",\"args\":{\"bill_type\":\"mortgage\",\"source_account\":\"savings\"}},{\"type\":\"launch\",\"fn\":\"modify_autopay\",\"args\":{\"bill_type\":\"credit_card\",\"source_account\":\"checking\"}}],\"say\": \"Updating your mortgage autopay to savings and setting up credit card payments from checking now.\"}", "infer": 0.795}, "4dc6ed7b6bfe987e9b3eed5643703ac76487db7e8e1e8e423349ddbeee05014f": {"raw": "{\"dialogue\": \"listen\", \"ops\": [{\"type\":\"patch\",\"op_id\":0,\"diff\":{\"source_account\":\"savings\"}}], \"say\": \"Updating the autopay to pull from savings now.\"}", "infer": 0.503}, "8fa540cf46451965817e03c50fd18892b0f62b3eaddef8cbd9286181b8f06837": {"raw": "{\"dialogue\": \"listen\", \"ops\": [{\"type\": \"launch\", \"fn\": \"search_apartments\", \"args\": {\"city\": \"Seattle\", \"bedrooms\": 2, \"max_price\": 2500}}], \"say\": \"\"}", "infer": 0.581}, "b81eaeef5c0d9babfc88b94c58cf6f89e084bd2488cdd67396b16dfd544098c9": {"raw": "{\"dialogue\": \"listen\", \"ops\": [{\"type\":\"launch\",\"fn\":\"calculate_commute\",\"args\":{\"origin_address\":\"101 Main Street\",\"destination_address\":\"Downtown Office\",\"mode\":\"driving\"}}], \"say\": \"Calculating your commute now.\"}", "infer": 0.583}, "32e159783350276c63d816839f9481fd428b508aac2597573d098739173f7ac7": {"raw": "{\"dialogue\": \"listen\", \"ops\": [], \"say\": \"\"}", "infer": 0.267}, "842cc648b97c36eb3aadb90669000a832e77a30662dee0ad49fccc4c6e99cb98": {"raw": "{\"dialogue\": \"listen\", \"ops\": [{\"type\":\"launch\",\"fn\":\"update_search_filter\",\"args\":{\"filter_name\":\"max_price\",\"value\":\"1800\"}}], \"say\": \"Updating your max price filter to $1800.\"}", "infer": 0.565}, "208499da0a28dfaac79bb184e680f54de401817dc0f310469e1ee1f041b6e0d6": {"raw": "{\"dialogue\": \"listen\", \"ops\": [], \"say\": \"\"}", "infer": 0.286}, "01dac9b644d5a8886f1f0ee828427103976947bb28c894e7fce10c65d7138002": {"raw": "{\"dialogue\": \"listen\", \"ops\": [], \"say\": \"\"}", "infer": 0.271}, "0842e194f11a1069b488ea64c054149db2549c3fc66e2e4176ceb0927ddc0783": {"raw": "{\"dialogue\": \"listen\", \"ops\": [], \"say\": \"\"}", "infer": 0.267}, "33f4cfa996addd6ce58358bcdb02f20290a3d5fb8ae5fb4ef71c4d5b7d45ece8": {"raw": "{\"dialogue\": \"listen\", \"ops\": [{\"type\":\"launch\",\"fn\":\"search_apartments\",\"args\":{\"city\":\"Denver\"}}], \"say\": \"Searching for apartments in Denver now.\"}", "infer": 0.456}, "eb06ea628d1dd5a449f6464c92d666761ba6258781b31ce3c47491c272c23d2d": {"raw": "{\"dialogue\": \"listen\", \"ops\": [{\"type\":\"patch\",\"op_id\":1,\"diff\":{\"bedrooms\":\"1\"}}], \"say\": \"\"}", "infer": 0.4}, "8bf774c212f53ca948a1071da5b0a0b20114c9f366e41d88f31f7485f97b9b0e": {"raw": "{\"dialogue\": \"listen\", \"ops\": [], \"say\": \"\"}", "infer": 0.277}, "9b6c3a9d13fe03458aa3d080a8a357555e9675f6168ff32786fbbe984d0e94ca": {"raw": "{\"dialogue\": \"listen\", \"ops\": [], \"say\": \"\"}", "infer": 0.291}, "eceea0de32b1ddbe1ba0767ff9be2691f04ad12e21a696225f6d8f9e3ad493aa": {"raw": "{\"dialogue\": \"listen\", \"ops\": [], \"say\": \"\"}", "infer": 0.269}, "1e4964075b709331cbb139d16fa31708b3ccd76ae6cae7a6d575df89ddaf1374": {"raw": "{\"dialogue\": \"listen\", \"ops\": [{\"type\":\"launch\",\"fn\":\"search_apartments\",\"args\":{\"city\":\"Miami\",\"pets_allowed\":true}}], \"say\": \"\"}", "infer": 0.447}, "bd7011589869715ff3e0066dc5aced7d34669db8e0127e885d5cda5bfc95b439": {"raw": "{\"dialogue\": \"listen\", \"ops\": [{\"type\":\"patch\",\"op_id\":1,\"diff\":{\"max_price\":1500}}], \"say\": \"\"}", "infer": 0.434}, "463211733617d2757d290879b69cbfe5d6ba172cf84d89167c05faaa0a325429": {"raw": "{\"dialogue\": \"listen\", \"ops\": [], \"say\": \"\"}", "infer": 0.29}, "f0492cbcc67d1bf028e97ccc669ede76af6fe724221baead589533ab9bf3e258": {"raw": "{\"dialogue\": \"listen\", \"ops\": [{\"type\":\"launch\",\"fn\":\"search_apartments\",\"args\":{\"city\":\"Miami\",\"bedrooms\":null,\"max_price\":null,\"pets_allowed\":true}}], \"say\": \"\"}", "infer": 0.536}, "d638c137e3527793faeebe6fe20390162259eef3545ec043e735ee1a3baf9f8a": {"raw": "{\"dialogue\": \"listen\", \"ops\": [{\"type\":\"patch\",\"op_id\":1,\"diff\":{\"max_price\":1500}}], \"say\": \"Updating your search with a $1500 monthly budget.\"}", "infer": 0.539}, "1287190ec4182118766d377fc9f5906b6917191cbb5e1d04efa8117d0047428b": {"raw": "{\"dialogue\": \"listen\", \"ops\": [{\"type\":\"launch\",\"fn\":\"calculate_commute\",\"args\":{\"origin_address\":\"Oak Street\",\"destination_address\":\"the gym\",\"mode\":\"walk\"}}], \"say\": \"Calculating the walking commute now.\"}", "infer": 0.549}, "82d3fe0d727fe60019cdcfb9d53d20beda444ca8c7950af8fb62e71557b0e755": {"raw": "{\"dialogue\": \"listen\", \"ops\": [], \"say\": \"\"}", "infer": 0.285}, "b0b09e0581101af613cf1195006547b11b284104f3e36f1a5496ef33f6dde0bf": {"raw": "{\"dialogue\": \"listen\", \"ops\": [], \"say\": \"\"}", "infer": 0.273}, "b1393e5972ddc344697efcd69bde735723747377b95847b9a6bfb27b5bf1f3d1": {"raw": "{\"dialogue\": \"listen\", \"ops\": [{\"type\":\"launch\",\"fn\":\"update_search_filter\",\"args\":{\"filter_name\":\"pets_allowed\",\"value\":\"true\"}}], \"say\": \"Updating your search filter to allow pets.\"}", "infer": 0.508}, "b640f8b084f39029d77d578d4e048df247ac16afb123f1aab5540f0ee9dad6ee": {"raw": "{\"dialogue\": \"listen\", \"ops\": [{\"type\":\"launch\",\"fn\":\"search_apartments\",\"args\":{\"city\":\"Chicago\",\"bedrooms\":2,\"max_price\":2000}}], \"say\": \"Looking for two-bedroom apartments in Chicago now.\"}", "infer": 0.586}, "3b8a2d9d73fe14c8e995fff0a16f559a8c1d16a9309b93213d8b475046ade7b3": {"raw": "{\"dialogue\": \"listen\", \"ops\": [{\"type\":\"launch\",\"fn\":\"calculate_commute\",\"args\":{\"origin_address\":\"500 Central Ave\",\"destination_address\":\"the university\",\"mode\":\"transit\"}}], \"say\": \"Calculating your transit commute now.\"}", "infer": 0.575}, "f1212817153dca4ee73b7e42eaeaf7f0cf34dffab0cedb12bbdaf09775b17802": {"raw": "{\"dialogue\": \"stay\", \"ops\": [{\"type\":\"launch\",\"fn\":\"calculate_commute\",\"args\":{\"origin_address\":\"500 Central Ave\",\"destination_address\":\"the university\",\"mode\":\"transit\"}},{\"type\":\"launch\",\"fn\":\"update_search_filter\",\"args\":{\"filter_name\":\"neighborhood\",\"value\":\"northside\"}}],\"say\": \"Checking your commute and updating your search filter now.\"}", "infer": 0.778}, "e3c1984f88c0ed0c49a8d5584047e496376329de62274cea48acf763ddb8b97a": {"raw": "{\"dialogue\": \"listen\", \"ops\": [{\"type\":\"launch\",\"fn\":\"search_apartments\",\"args\":{\"city\":\"New York City\",\"bedrooms\":2,\"max_price\":1600}}], \"say\": \"Searching for two-bedroom apartments up to $1,600 per month.\"}", "infer": 0.64}, "d70d68d35aa145292b7d62328b1b31bcdb45d1a4e1824fcd2161b9aa10887bcc": {"raw": "{\"dialogue\": \"listen\", \"ops\": [{\"type\":\"launch\",\"fn\":\"update_search_filter\",\"args\":{\"filter_name\":\"max_price\",\"value\":\"3000\"}}], \"say\": \"Updating the max price filter to 3,000 per month.\"}", "infer": 0.58}, "4e5d04aa83cfd58e2d129afa9b90c38a80718195fc7bd67e9d2970e1f30036e0": {"raw": "{\"dialogue\": \"listen\", \"ops\": [{\"type\":\"patch\",\"op_id\":1,\"diff\":{\"value\":3000}},{\"type\":\"launch\",\"fn\":\"update_search_filter\",\"args\":{\"filter_name\":\"bedrooms\",\"value\":3}}], \"say\": \"Updating the max price and setting minimum bedrooms to three.\"}", "infer": 0.669}, "38681f77ffb244ffcf6ee93f555cdde6659aea1efd8d60119babd3b17c590330": {"raw": "{\"dialogue\": \"stay\", \"ops\": [], \"say\": \"\"}", "infer": 0.287}, "73b42f7d00b0a08efae36f353c8e5de7f95653ad5d4f015b6f46e054edb65e7e": {"raw": "{\"dialogue\": \"listen\", \"ops\": [{\"type\":\"launch\",\"fn\":\"search_apartments\",\"args\":{\"city\":\"Portland\",\"bedrooms\":1,\"max_price\":1800,\"pets_allowed\":true}}], \"say\": \"Searching for pet-friendly one-bedroom apartments under $1800 in Portland now.\"}", "infer": 0.682}, "1a3f97a80598f6662af9fba0529a3bb57c0811f8149b813c688ab3dd87bc423f": {"raw": "{\"dialogue\": \"listen\", \"ops\": [{\"type\":\"launch\",\"fn\":\"search_apartments\",\"args\":{\"city\":\"Portland\",\"bedrooms\":1,\"max_price\":1800,\"pets_allowed\":true}}], \"say\": \"Searching for pet-friendly one-bedroom apartments under $1800 in Portland now.\"}", "infer": 0.689}, "9ecc1ad02d90eb2e51c67ab9cb97c440b1d8800db2286fbb803ad12df5fdcf9a": {"raw": "{\"dialogue\": \"listen\", \"ops\": [], \"say\": \"\"}", "infer": 0.304}, "a9f3587d17e57de62201539e854e4f79d688462d1dc9b848f4d12bfa98c75ece": {"raw": "{\"dialogue\": \"listen\", \"ops\": [], \"say\": \"\"}", "infer": 0.269}, "7b82a74ce8fc226e99f33b4673fb62de87856a3cdcfddae583f6ec0d1f8cab0e": {"raw": "{\"dialogue\": \"listen\", \"ops\": [{\"type\":\"launch\",\"fn\":\"search_apartments\",\"args\":{\"city\":\"Atlanta\",\"bedrooms\":3,\"max_price\":null,\"pets_allowed\":true}}], \"say\": \"Searching for pet-friendly 3-bedroom apartments in Atlanta now.\"}", "infer": 0.621}, "845c63718a5be0d5485ba300bffd0f850cba05e64a0174e169a2ce594f0ad8e4": {"raw": "{\"dialogue\": \"listen\", \"ops\": [{\"type\":\"launch\",\"fn\":\"search_apartments\",\"args\":{\"city\":\"Atlanta\",\"bedrooms\":3,\"max_price\":null,\"pets_allowed\":true}}], \"say\": \"Searching for pet-friendly 3-bedroom apartments in Atlanta now.\"}", "infer": 0.627}, "c33c8276a08e0022f2b40f8f7be7c9778588588a74ef60fbc99e2ff700c85851": {"raw": "{\"dialogue\": \"listen\", \"ops\": [], \"say\": \"\"}", "infer": 0.297}, "0d9f394faa61e8f5e61824dec597916b36247cdca1747010fe835002d8d26988": {"raw": "{\"dialogue\": \"listen\", \"ops\": [{\"type\":\"launch\",\"fn\":\"search_apartments\",\"args\":{\"city\": \"Atlanta\", \"bedrooms\": 3, \"max_price\": null, \"pets_allowed\": true}}], \"say\": \"Searching for pet-friendly apartments in Atlanta.\"}", "infer": 0.649}, "c03227c0c967870adead3de82a5763654a52f1a42d2de9fcd55c387d4806792d": {"raw": "{\"dialogue\": \"listen\", \"ops\": [{\"type\":\"launch\",\"fn\":\"search_apartments\",\"args\":{\"city\": \"Atlanta\", \"bedrooms\": 3, \"max_price\": null, \"pets_allowed\": true}}], \"say\": \"\"}", "infer": 0.586}, "388bc4f9a4965c6b2358ad1cc6d3d29e2c870a310b25c043f83c5c3513118d6b": {"raw": "{\"dialogue\": \"listen\", \"ops\": [{\"type\":\"launch\",\"fn\":\"calculate_commute\",\"args\":{\"origin_address\":\"my house\",\"destination_address\":\"the office\",\"mode\":\"driving\"}}], \"say\": \"Calculating driving time from your house to the office now.\"}", "infer": 0.603}, "18efbd5bb3aef60bbeca4aeac059b33891a024d2556020b28204f4c033aacec7": {"raw": "{\"dialogue\": \"listen\", \"ops\": [{\"type\":\"launch\",\"fn\":\"calculate_commute\",\"args\":{\"origin_address\":\"there\",\"destination_address\":\"the office\"}}], \"say\": \"Calculating the commute time now.\"}", "infer": 0.508}, "ddd8f66ee979245ea8fe304a1b6325d2085a8b43f876cad6e8ba43100cfc1ea1": {"raw": "{\"dialogue\": \"listen\", \"ops\": [{\"type\":\"patch\",\"op_id\":1,\"diff\":{\"origin_address\":\"there\",\"destination_address\":\"the office\"}}], \"say\": \"\"}", "infer": 0.441}, "9682e7c5a61cf27934504b62b5392a9e000204462a875d356d2ea4f49e93c5a1": {"raw": "{\"dialogue\": \"listen\", \"ops\": [{\"type\":\"patch\",\"op_id\":1,\"diff\":{\"origin_address\":\"my house\",\"destination_address\":\"the office\",\"mode\":\"driving\"}}], \"say\": \"Updating that to driving from my house to the office.\"}", "infer": 0.576}, "57f774d97c3e60c39659eb80032467dbcb6f9e21bb2cd5bac1792bbe78b8a603": {"raw": "{\"dialogue\": \"listen\", \"ops\": [{\"type\":\"launch\",\"fn\":\"search_apartments\",\"args\":{\"city\":\"Portland\",\"bedrooms\":1,\"max_price\":800}},{\"type\":\"launch\",\"fn\":\"calculate_commute\",\"args\":{\"origin_address\":\"$RESULT_0.properties[0].address\",\"destination_address\":\"Fifth Street Coffee Shop\",\"mode\":\"bike\"}}],\"say\": \"Searching for apartments and calculating the commute now.\"}", "infer": 0.853}, "797753beab5b65f542022c8359ffc9753ba10eec39bc3a83768fa5a66e3f5c1c": {"raw": "{\"dialogue\": \"listen\", \"ops\": [{\"type\":\"launch\",\"fn\":\"calculate_commute\",\"args\":{\"origin_address\":\"my house\",\"destination_address\":\"the gym\",\"mode\":\"driving\"}}], \"say\": \"Calculating your driving commute to the gym now.\"}", "infer": 0.579}, "1b57e081c573ac1c1277b12044d3250237c7fc5fa9f94c9f1aad36e4f1b849d1": {"raw": "{\"dialogue\": \"listen\", \"ops\": [{\"type\":\"launch\",\"fn\":\"search_apartments\",\"args\":{\"city\":\"Austin\",\"max_price\":2000,\"bedrooms\":null,\"pets_allowed\":null}},{\"type\":\"launch\",\"fn\":\"calculate_commute\",\"args\":{\"origin_address\":\"my office\",\"destination_address\":\"\",\"mode\":\"\"}}],\"say\": \"\"}", "infer": 0.736}, "76b5c58f5ee97a2e27d1a6f32410b2d60afbee927eb0f916b7b2c3fa5055cb3c": {"raw": "{\"dialogue\": \"listen\", \"ops\": [{\"type\":\"launch\",\"fn\":\"search_apartments\",\"args\":{\"city\":\"New York City\",\"bedrooms\":3,\"max_price\":null,\"pets_allowed\":null}},{\"type\":\"patch\",\"op_id\":0,\"diff\":{\"bedrooms\":3}}],\"say\":\"\"}", "infer": 0.662}, "9839d816fce3aed1a9d450d06ff5b615cba4050fc8c9a386e3b45a79187467b2": {"raw": "{\"dialogue\": \"listen\", \"ops\": [{\"type\":\"patch\",\"op_id\":1,\"diff\":{\"bedrooms\":3}},{\"type\":\"launch\",\"fn\":\"calculate_commute\",\"args\":{\"origin_address\":\"New York City\",\"destination_address\":\"train station\",\"mode\":\"walking\"}}],\"say\": \"Updating that to three bedrooms and checking the walking commute now.\"}", "infer": 0.718}, "cf596e948098ea4aa410a085a633f4bd51ccc9fb85702907c8e6a423ed1b8ceb": {"raw": "{\"dialogue\": \"listen\", \"ops\": [{\"type\":\"launch\",\"fn\":\"update_search_filter\",\"args\":{\"filter_name\":\"pets_allowed\",\"value\":\"true\"}}], \"say\": \"Updating your search filter to allow pets.\"}", "infer": 0.509}, "ca41a0865096c7bc65a8910843ce0b43df4572092ca21312e1e1318cd278d060": {"raw": "{\"dialogue\": \"listen\", \"ops\": [{\"type\":\"commit\",\"op_id\":1},{\"type\":\"launch\",\"fn\":\"search_apartments\",\"args\":{\"city\":\"Seattle\",\"bedrooms\":1,\"max_price\":null,\"pets_allowed\":true}}], \"say\": \"Updating your filter and searching for one-bedroom apartments in Seattle now.\"}", "infer": 0.689}, "421ecd31e2eb65936e1abbf011731f0da14dc5e52b1f0c8651df7890c0f8bb30": {"raw": "{\"dialogue\": \"listen\", \"ops\": [], \"say\": \"\"}", "infer": 0.295}, "cd2d061e926ca1a0ef94503ea8dc4b4183f85bd35bb0769372555b9a8750e206": {"raw": "{\"dialogue\": \"listen\", \"ops\": [], \"say\": \"\"}", "infer": 0.27}, "6fb32ef020277dbbb9f9f808e233374d9d1069b196c1dc87b83c4f16416cc372": {"raw": "{\"dialogue\": \"listen\", \"ops\": [{\"type\":\"patch\",\"op_id\":0,\"diff\":{\"max_price\":1500}},{\"type\":\"launch\",\"fn\":\"search_apartments\",\"args\":{\"city\":\"Dallas\",\"bedrooms\":null,\"max_price\":1500}}],\"say\": \"Updating your max price and searching for Dallas apartments now.\"}", "infer": 0.737}, "090cd3a85f18973e0a149617d5d1d0b33e53577b6ce2272708acba78315a025d": {"raw": "{\"dialogue\": \"listen\", \"ops\": [{\"type\":\"patch\",\"op_id\":1,\"diff\":{\"max_price\":1500}}],\"say\": \"Updating your max price to $1500 and searching Dallas apartments now.\"}", "infer": 0.561}, "be1354e2d63974bb58a7eb66b40b0ebcac2aa7d8037eff706d4277ae7cc0682c": {"raw": "{\"dialogue\": \"listen\", \"ops\": [{\"type\":\"launch\",\"fn\":\"update_search_filter\",\"args\":{\"filter_name\":\"max_price\",\"value\":\"1500\"}}], \"say\": \"Updating your max price filter to 1500.\"}", "infer": 0.569}, "16218ee7b3027d9e6f50a0be3b45b1ac89bb47daec914099ead91179fd2df7b3": {"raw": "{\"dialogue\": \"stay\", \"ops\": [], \"say\": \"\"}", "infer": 0.28}, "3050b7f83f270454acf5429c7d9be3cbe2a4ef9bc998ec9feeb1b4c0941a3865": {"raw": "{\"dialogue\": \"listen\", \"ops\": [{\"type\":\"launch\",\"fn\":\"update_search_filter\",\"args\":{\"filter_name\": \"max_price\", \"value\": 1500}}, {\"type\":\"launch\",\"fn\":\"search_apartments\",\"args\":{\"city\": \"Dallas\", \"max_price\": 1500}}], \"say\": \"\"}", "infer": 0.72}, "1a2c897f598dec897848573e1d56175bcb7aad0262dc0b2009a3966b8ea74bc8": {"raw": "{\"dialogue\": \"listen\", \"ops\": [], \"say\": \"\"}", "infer": 0.297}, "774c2c14174863a0a0e8e33cfcc3411ba8cabb48a7a1d2ba0c4d581488554480": {"raw": "{\"dialogue\": \"listen\", \"ops\": [], \"say\": \"\"}", "infer": 0.306}, "f765dd2d6700262b2bec08de906f63f4638a115f2890b8c3aebe50a60394c34f": {"raw": "{\"dialogue\": \"listen\", \"ops\": [{\"type\":\"launch\",\"fn\":\"update_search_filter\",\"args\":{\"filter_name\":\"pets_allowed\",\"value\":\"true\"}},{\"type\":\"launch\",\"fn\":\"update_search_filter\",\"args\":{\"filter_name\":\"max_price\",\"value\":3000}}], \"say\": \"\"}", "infer": 0.638}, "dd1f8306f8349d9ff7a6b617003e1213b07ba468b39e6e1750752bd43c3faea6": {"raw": "{\"dialogue\": \"listen\", \"ops\": [{\"type\":\"patch\",\"op_id\":2,\"diff\":{\"args\":{\"value\":3500}}},{\"type\":\"launch\",\"fn\":\"search_apartments\",\"args\":{\"city\":\"San Francisco\",\"bedrooms\":null,\"max_price\":3500,\"pets_allowed\":true}}],\"say\": \"Updating the max price to 3500 and searching for apartments in San Francisco now.\"}", "infer": 0.855}, "ca5989f528b3304f808d29fd93ec528739d0a88065e74b1f20e93e831696f77e": {"raw": "{\"dialogue\": \"listen\", \"ops\": [{\"type\":\"launch\",\"fn\":\"search_flights\",\"args\":{\"destination\":\"Tokyo\",\"date\":\"July 15\"}}], \"say\": \"Looking up flights to Tokyo for July 15 now.\"}", "infer": 0.558}, "c7a31b1e159c65af25b3362902a1c3e4aecef6077487bb49e91ad69a9f38f8c7": {"raw": "{\"dialogue\": \"listen\", \"ops\": [{\"type\":\"launch\",\"fn\":\"update_identity_doc\",\"args\":{\"doc_type\":\"passport\",\"doc_number\":\"P88990011\"}}], \"say\": \"Updating your passport number now.\"}", "infer": 0.556}, "133ea39a1e1959958c38ed03c7bec81472c8134282d8da210c296e12604f0552": {"raw": "{\"dialogue\": \"listen\", \"ops\": [{\"type\":\"commit\",\"op_id\":1}], \"say\": \"\"}", "infer": 0.356}, "bbfd78e3e2feb068df53fdec3ae9faadcb63f079053e5d65d1cb3ba65dd70c56": {"raw": "{\"dialogue\": \"listen\", \"ops\": [], \"say\": \"\"}", "infer": 0.272}, "dbee9bbaa33b7ad2da277f88d37368fec060f4495a2cfb7df6e1bc771b4d756c": {"raw": "{\"dialogue\": \"listen\", \"ops\": [{\"type\":\"launch\",\"fn\":\"search_flights\",\"args\":{\"destination\":\"London\",\"date\":\"August 20th\"}}], \"say\": \"Checking flights to London for August 20th now.\"}", "infer": 0.555}, "5644806a54eb052eb25684ed6377261bf2a1d0587274371cb30471012bb505af": {"raw": "{\"dialogue\": \"listen\", \"ops\": [{\"type\":\"launch\",\"fn\":\"search_flights\",\"args\":{\"destination\":\"London\",\"date\":\"August 20th\"}}], \"say\": \"Checking flights to London for August 20th now.\"}", "infer": 0.557}, "4fd08d788793fd76cc0f97491511380e64d65347e8298ac9858ca6ea098d879f": {"raw": "{\"dialogue\": \"listen\", \"ops\": [{\"type\":\"launch\",\"fn\":\"search_flights\",\"args\":{\"destination\":\"Chicago\",\"date\":\"December 12th\"}}], \"say\": \"Looking up flights to Chicago for December 12th now.\"}", "infer": 0.561}, "c2be6c04d8f2430f1fd579517f2313979a36189ff73c00dee1a0e287b4787f2e": {"raw": "{\"dialogue\": \"listen\", \"ops\": [{\"type\":\"launch\",\"fn\":\"update_identity_doc\",\"args\":{\"doc_type\":\"driver license\",\"doc_number\":\"D-L-5-5-5\"}}], \"say\": \"Updating your driver's license now.\"}", "infer": 0.568}, "1a7a577f7f0bcf2082eb2f5b2ad65159b87e9be6baec40fddabffd7562b614e2": {"raw": "{\"dialogue\": \"listen\", \"ops\": [{\"type\":\"launch\",\"fn\":\"update_identity_doc\",\"args\":{\"doc_type\":\"driver license\",\"doc_number\":\"DL\"}}], \"say\": \"\"}", "infer": 0.452}, "0fd3eb7149263935b38bb5d2877bb2c8f10bc430c83ad3db87343ca42ab155b3": {"raw": "{\"dialogue\": \"listen\", \"ops\": [{\"type\":\"patch\",\"op_id\":1,\"diff\":{\"doc_number\":\"DL555\"}}], \"say\": \"Updating your driver license to DL555 now.\"}", "infer": 0.506}, "f7d4afd39937b64b3dfd2f0dcc2fbf75471ea329f87b3c84a177c352fd5d1e7e": {"raw": "{\"dialogue\": \"listen\", \"ops\": [], \"say\": \"\"}", "infer": 0.27}, "d99591284654dbd7955b473e6e5902e739290866a417a51f401923a05f26caac": {"raw": "{\"dialogue\": \"listen\", \"ops\": [{\"type\":\"launch\",\"fn\":\"search_flights\",\"args\":{\"destination\":\"Seattle\"}}], \"say\": \"Searching for flights to Seattle now.\"}", "infer": 0.453}, "1be91e9a8d3ded5da45e7839d6af6da6dff0ef3cd883625016e1658ad9980521": {"raw": "{\"dialogue\": \"listen\", \"ops\": [{\"type\":\"patch\",\"op_id\":1,\"diff\":{\"destination\":\"Seattle\",\"date\":\"November 1st\"}}], \"say\": \"Updating that to Seattle on November 1st.\"}", "infer": 0.52}, "c3dfe87ffef5cc1e54a6f8f9642caf379a793f0dc30880c2c40791457ce175d5": {"raw": "{\"dialogue\": \"listen\", \"ops\": [{\"type\":\"launch\",\"fn\":\"search_flights\",\"args\":{\"destination\":\"Miami\",\"date\":\"October 5th\"}}], \"say\": \"Searching for flights to Miami on October 5th now.\"}", "infer": 0.539}, "a3ffdc408f52715f7a5fde24b72297db2ddb53c0e593d643a06532cf0d1ce7b6": {"raw": "{\"dialogue\": \"listen\", \"ops\": [], \"say\": \"\"}", "infer": 0.266}, "277df5869b8839fcf3de6e3142834bff41923c041112a25db1bbccb46ea10de9": {"raw": "{\"dialogue\": \"listen\", \"ops\": [{\"type\":\"patch\",\"op_id\":1,\"diff\":{\"date\":\"October 7th\"}}], \"say\": \"Updating that to October 7th.\"}", "infer": 0.488}, "bfb455d816b6923fc6565a03bbcd84d5142eb99952abfe729d09b31aae19b1dd": {"raw": "{\"dialogue\": \"listen\", \"ops\": [{\"type\":\"launch\",\"fn\":\"search_flights\",\"args\":{\"destination\":\"Austin\",\"date\":\"February 2nd\"}},{\"type\":\"launch\",\"fn\":\"book_flight\",\"args\":{\"passenger_name\":\"Morgan Smith\"}}], \"say\": \"\"}", "infer": 0.608}, "6fcd367bd35e548db7309950f0db2ebcf8ab7d4970a70d98a1f48081c2636f13": {"raw": "{\"dialogue\": \"listen\", \"ops\": [{\"type\":\"launch\",\"fn\":\"search_flights\",\"args\":{\"destination\":\"Seoul\",\"date\":\"March 22\"}}], \"say\": \"Searching for flights to Seoul on March 22.\"}", "infer": 0.548}, "c6abcf936ad66c9ff60796ef6090a53d7cf23fc376815fcd12d6c56189031a97": {"raw": "{\"dialogue\": \"listen\", \"ops\": [{\"type\":\"launch\",\"fn\":\"search_flights\",\"args\":{\"destination\":\"Las Vegas\",\"date\":\"August 8\"}}], \"say\": \"Searching for flights to Las Vegas on August 8 now.\"}", "infer": 0.553}, "fc7bf09db973e67cb282b247849880b765391d95746a04136e64a53c0bdaedf2": {"raw": "{\"dialogue\": \"listen\", \"ops\": [{\"type\":\"launch\",\"fn\":\"search_flights\",\"args\":{\"destination\":\"Dubai\",\"date\":\"April 10\"}}], \"say\": \"Searching for flights to Dubai on April 10 now.\"}", "infer": 0.553}, "7ee7c01cecf0d493c5edb5b3e0952230ccdd75efa35772941de9c6a07c751469": {"raw": "{\"dialogue\": \"listen\", \"ops\": [{\"type\":\"launch\",\"fn\":\"search_flights\",\"args\":{\"destination\":\"Dubai\",\"date\":\"April 10\"}},{\"type\":\"launch\",\"fn\":\"book_flight\",\"args\":{\"passenger_name\":\"Casey Lee\"}},{\"type\":\"launch\",\"fn\":\"update_identity_doc\",\"args\":{\"doc_type\":\"passport\",\"doc_number\":\"E772211\"}}],\"say\": \"\"}", "infer": 0.832}, "df8af536b95b6e21051767aeb2bb6ee72caac67b7ce9d7b51ecfac36471d5fbc": {"raw": "{\"dialogue\": \"listen\", \"ops\": [{\"type\": \"launch\", \"fn\": \"search_flights\", \"args\": {\"destination\": \"Rome\"}}], \"say\": \"\"}", "infer": 0.454}, "e4aabf8ebfcc5cfe406bd0773b195a1d327d51785d4634a8128c7466fcd02348": {"raw": "{\"dialogue\": \"listen\", \"ops\": [{\"type\":\"patch\",\"op_id\":1,\"diff\":{\"args\":{\"destination\":\"Milan\"}}}, {\"type\":\"commit\",\"op_id\":1}], \"say\": \"Updating that to Milan and checking the flights now.\"}", "infer": 0.557}, "f23fff3c5cba4f076a4992d74ff4d6b1da209f5c1091c6cebf0f45cff5ec3b18": {"raw": "{\"dialogue\": \"stay\", \"ops\": [{\"type\":\"patch\",\"op_id\":1,\"diff\":{\"destination\":\"Milan\"}}, {\"type\":\"launch\",\"fn\":\"search_flights\",\"args\":{\"destination\":\"Milan\",\"date\":\"June 1\"}}], \"say\": \"Updating that to Milan and checking flights now.\"}", "infer": 0.655}, "89b828e38dd8d061753f78ba314845f2d48f3def1b10d0a16f98a455dc71fae9": {"raw": "{\"dialogue\": \"listen\", \"ops\": [{\"type\":\"patch\",\"op_id\":2,\"diff\":{\"date\":\"June 3\"}}, {\"type\":\"commit\",\"op_id\":2}], \"say\": \"Updating that to June 3rd and checking flights now.\"}", "infer": 0.58}, "d12b5cdc4514f2a0f921a557f8c35fcda290ac5b60d74125005fda8489992498": {"raw": "{\"dialogue\": \"listen\", \"ops\": [{\"type\":\"patch\",\"op_id\":1,\"diff\":{\"destination\":\"Milan\"}},{\"type\":\"patch\",\"op_id\":2,\"diff\":{\"date\":\"June 3\"}}], \"say\": \"\"}", "infer": 0.551}, "7b4e57984a2cbb3c986023378295229bf6ecc52eed2a3e9e15239c5c8e279a80": {"raw": "{\"dialogue\": \"listen\", \"ops\": [{\"type\":\"launch\",\"fn\":\"search_flights\",\"args\":{\"destination\":\"Toronto\",\"date\":\"July 20\"}},{\"type\":\"launch\",\"fn\":\"update_identity_doc\",\"args\":{\"doc_type\":\"driver license\",\"doc_number\":\"DL88\"}}],\"say\": \"\"}", "infer": 0.661}, "235e816d51d257b339249fb60c3f11dbac7a143f8b43d02fa362be7bc414d901": {"raw": "{\"dialogue\": \"listen\", \"ops\": [{\"type\":\"launch\",\"fn\":\"search_flights\",\"args\":{\"destination\":\"Las Vegas\",\"date\":\"August 8\"}},{\"type\":\"launch\",\"fn\":\"book_flight\",\"args\":{\"passenger_name\":\"Quinn Davis\"}},{\"type\":\"launch\",\"fn\":\"update_identity_doc\",\"args\":{\"doc_type\":\"visa number\",\"doc_number\":\"V77\"}}],\"say\": \"\"}", "infer": 0.81}, "7e37caca46f4226c3f5fa60a1e97ffd6a1356fb1bca247876d452fd3a1a0f643": {"raw": "{\"dialogue\": \"listen\", \"ops\": [], \"say\": \"\"}", "infer": 0.273}, "017d48938cd0ae049ea25d2414feb14cc088af0e01cad596de8ce1b294aae233": {"raw": "{\"dialogue\": \"listen\", \"ops\": [], \"say\": \"\"}", "infer": 0.276}, "0eda9946f7999ce6d06150c7c0713441d7e4edc2e3641c54be6a5e7be08038d0": {"raw": "{\"dialogue\": \"listen\", \"ops\": [], \"say\": \"\"}", "infer": 0.274}, "ca6e119c5b82fb134e1c5a44db6edcdeb469e8d9eea369d032ae7aa1c484a44f": {"raw": "{\"dialogue\": \"listen\", \"ops\": [{\"type\": \"launch\", \"fn\": \"search_flights\", \"args\": {\"destination\": \"Las Vegas\", \"date\": \"August 8\"}}], \"say\": \"\"}", "infer": 0.512}, "fd46cc7905cc25dd5e70149c4f6b0d75f0fc7b097c7f2af1fc2e439a4f9f8746": {"raw": "{\"dialogue\": \"listen\", \"ops\": [{\"type\":\"launch\",\"fn\":\"search_flights\",\"args\":{\"destination\":\"Las Vegas\",\"date\":\"August 8\"}},{\"type\":\"launch\",\"fn\":\"book_flight\",\"args\":{\"passenger_name\":\"Quinn Davis\"}}],\"say\": \"\"}", "infer": 0.606}, "33d2bc3f1995b6837d2bbd83b61e0d88bb2bc69d35a23559d5a74ff54e26f874": {"raw": "{\"dialogue\": \"listen\", \"ops\": [{\"type\":\"launch\",\"fn\":\"update_identity_doc\",\"args\":{\"doc_type\":\"visa\",\"doc_number\":\"V77\"}}, {\"type\":\"commit\",\"op_id\":1}, {\"type\":\"commit\",\"op_id\":2}], \"say\": \"Searching flights to Las Vegas for August 8 and booking under Quinn Davis. Updating your visa number now.\"}", "infer": 0.789}, "5dab2b3ff5e629c7b268ca00334b7fe1b46f6e89e39ce8afc6e6a13915de1785": {"raw": "{\"dialogue\": \"listen\", \"ops\": [], \"say\": \"\"}", "infer": 0.271}, "e3e684465757dc973c1636a630c26cca07e64fa5f7e9b70c4a28de957e88801b": {"raw": "{\"dialogue\": \"listen\", \"ops\": [{\"type\":\"launch\",\"fn\":\"update_identity_doc\",\"args\":{\"doc_type\":\"passport\",\"doc_number\":\"P1122\"}},{\"type\":\"launch\",\"fn\":\"update_identity_doc\",\"args\":{\"doc_type\":\"driver license\",\"doc_number\":\"DL9090\"}}],\"say\": \"Updating both your passport and driver's license now.\"}", "infer": 0.767}, "f6d84ceb6137439ba5147b4d6dee07f73b52ab77d808f10a38285f24688fa685": {"raw": "{\"dialogue\": \"listen\", \"ops\": [], \"say\": \"\"}", "infer": 0.272}, "0d1cb2d81edf689c80394123ed18016ad202dd1d0cdd98ebbcac648f2b6f598f": {"raw": "{\"dialogue\": \"listen\", \"ops\": [{\"type\":\"launch\",\"fn\":\"update_identity_doc\",\"args\":{\"doc_type\":\"passport\",\"doc_number\":\"P1122\"}}], \"say\": \"Updating your passport number now.\"}", "infer": 0.518}, "182294e4cdae3afa6b1d26029ccf72de72ead5fdc18defe1a5b76edf1226fa59": {"raw": "{\"dialogue\": \"listen\", \"ops\": [], \"say\": \"\"}", "infer": 0.279}, "2971199f8c24f1eb8b9087af51ba6de403dd7941c06c50b39d452140df494325": {"raw": "{\"dialogue\": \"listen\", \"ops\": [{\"type\":\"patch\",\"op_id\":1,\"diff\":{\"doc_number\":\"P1122\"}},{\"type\":\"launch\",\"fn\":\"update_identity_doc\",\"args\":{\"doc_type\":\"driver license\",\"doc_number\":\"DL9090\"}}],\"say\": \"Updating your passport and driver's license now.\"}", "infer": 0.716}, "6b519d0994c6cf1dd172838640710c7380cc69fde180a51eee5722be725ad4b3": {"raw": "{\"dialogue\": \"listen\", \"ops\": [{\"type\":\"launch\",\"fn\":\"search_flights\",\"args\":{\"destination\":\"Vancouver\",\"date\":\"November 5th\"}}], \"say\": \"Searching for flights to Vancouver on November 5th now.\"}", "infer": 0.549}, "f693866fa3aeda9269297c54e0c034e74f0fe2264d5138d6adac5ad126e69e2e": {"raw": "{\"dialogue\": \"listen\", \"ops\": [{\"type\":\"launch\",\"fn\":\"search_flights\",\"args\":{\"destination\":\"Vancouver\",\"date\":\"November 5th\"}},{\"type\":\"launch\",\"fn\":\"book_flight\",\"args\":{\"passenger_name\":\"Skylar\"}}], \"say\": \"\"}", "infer": 0.616}, "d4c7cc27c3019dd0dbd82e2079dff6be956298e1dd782d1f18a3ea9f59987698": {"raw": "{\"dialogue\": \"listen\", \"ops\": [{\"type\":\"launch\",\"fn\":\"search_flights\",\"args\":{\"destination\":\"Vancouver\",\"date\":\"November 5th\"}},{\"type\":\"patch\",\"op_id\":1,\"diff\":{\"passenger_name\":\"Skylar\"}}], \"say\": \"\"}", "infer": 0.624}, "ebd88393c62e8e2f0c6b226179fd36be73a800ce173fb209feb4f8b243b68c2e": {"raw": "{\"dialogue\": \"listen\", \"ops\": [{\"type\":\"launch\",\"fn\":\"search_flights\",\"args\":{\"destination\":\"Vancouver\",\"date\":\"November 5th\"}},{\"type\":\"commit\",\"op_id\":1},{\"type\":\"launch\",\"fn\":\"search_apartments\",\"args\":{\"city\":\"Vancouver\",\"pets_allowed\":false,\"max_price\":200,\"bedrooms\":1}},{\"type\":\"launch\",\"fn\":\"update_identity_doc\",\"args\":{\"doc_type\":\"visa\",\"doc_number\":\"V-4-4\"}}],\"say\": \"\"}", "infer": 1.02}}